analytics/__init__.py
analytics/client.py
analytics/consumer.py
analytics/request.py
analytics/utils.py
analytics/version.py
analytics/test/__init__.py
analytics/test/client.py
analytics/test/consumer.py
analytics/test/module.py
analytics/test/request.py
analytics/test/utils.py
analytics_python-1.3.1.dist-info/METADATA
analytics_python-1.3.1.dist-info/WHEEL
analytics_python-1.3.1.dist-info/top_level.txt
analytics_python-1.3.1.dist-info/RECORD
